comby/__init__.py
comby/binary.py
comby/core.py
comby/exceptions.py
comby/interface.py
comby-0.0.2.dist-info/LICENSE
comby-0.0.2.dist-info/METADATA
comby-0.0.2.dist-info/WHEEL
comby-0.0.2.dist-info/top_level.txt
comby-0.0.2.dist-info/RECORD
