Metadata-Version: 2.1
Name: comby
Version: 0.0.2
Summary: Lightweight language-independent syntax rewriting.
Home-page: https://github.com/ChrisTimperley/comby-python
Author: Christopher Timperley
Author-email: christimperley@googlemail.com
License: MIT
Keywords: rewrite,syntax,comby,transformation
Platform: UNKNOWN
Classifier: Natural Language :: English
Classifier: Intended Audience :: Developers
Classifier: Programming Language :: Python
Classifier: Programming Language :: Python :: 3
Classifier: Programming Language :: Python :: 3.6
Classifier: Programming Language :: Python :: 3.7
Classifier: Programming Language :: Python :: 3.8
Requires-Python: >=3.6
Requires-Dist: attrs (>=19.2.0)
Requires-Dist: loguru (~=0.4)
Requires-Dist: requests (~=2.0)
Requires-Dist: typing (>=0.4)
